{
  "name": "Sam Nash",
  "age": 41,
  "address": {
    "street": "Sinu Plaza",
    "city": "Mezuvnuh",
    "state": "RI",
    "zip": "77770"
  },
  "contact": {
    "phone": "(711) 903-4586",
    "servicePhone": "800688789"
  },
  "birthday": "1977-10-18T20:25:49.363Z",
  "ip": "17.109.107.48",
  "foo": "bar",
  "profile": {
    "about": "Acimewoh kokono hugizbec odukita jiggaz rilopa rohkavob asjeforo abpe cumwir oc otowuj neforaji vogvij. Saguz alze cabugtem raip mintebif fak figu zez kuhetiki ehemal gub wuwut ar giktais. Haucotog taucu gurku tate werulazi ubeudafap hol ucti bocec ruvzog gumzufzil dalgicuku joakozog.",
    "bio": "Ik uw dih som socso an ledvufmaw dorgufe bamodaba vuwnogob gusi zourjek fen suzbumav tu tojjagfab. Mosapit zoh sodajo kuce moudame hacav wuw kulatere legronris de vepege iha bavup om fuwop fahmir ropa. Pevav ramov hunabo otohse ago im ca eze dov le rujlicis lela. Metut kaemisa nonres bohohu uzra ho ju gi wanas dimjatcab leccujtip mowkikab obno nepvic lutusuj zurhewuw zu. Hifieg kedar aso mi nujwah na podorlon ruvaw mitosa meprasle biv evzuna jiwmu vaez jamodosa."
  },
  "apiKey": "8b0012e838affb4557c91cf11d79dc0e1781c11ce43f8db445a2b588f96bab60",
  "currency": {
    "code": "BBD",
    "name": "Barbados Dollar"
  }
}