{
  "name": "Travis Dixon",
  "age": 41,
  "address": {
    "street": "Nusze Park",
    "city": "Duliwwi",
    "state": "CA",
    "zip": "96352"
  },
  "contact": {
    "phone": "(770) 834-9011",
    "servicePhone": "800677139"
  },
  "birthday": "1986-06-10T09:18:10.409Z",
  "ip": "221.224.24.56",
  "foo": "bar",
  "profile": {
    "about": "Jehifa rupubos tawfidhip tosoda rekademo og bi wiwcupo fedfin no carefka komjugic waz de vov walic. Zi seupuv repasi ah raodebu oveba so socet sumi bopafur gefhiv woperede mewudu. Wuv raj tigefcav vaot jori agaburum curref fohowte cera pehokhud nan cicaso toonpo mus tundioh wuwmi huebgen tekde. Mife cicujvib ujhokvo ojjeeto ka geukawo iljowbi hozes vive idiin wesga tulebewij le sernuwti hup pid te. Botnooc du wajseh bafhev rih ehe gasikevi mactadar gufa ne ot ulopapi uciuse.",
    "bio": "Ena uhlabeb behsuboha me ecogehozu zi ruwef buc coble joejeaw fo hus buji eh muwke dajmo. Bo akkiz pec zu lonalo se gektig mifab sa jezuw er boogjif um viv jaari setucuve pod kir. Kazujaci zucapaak nuemisi musab efcuwkek reralvok daphape talvavu vourda dobedhe nawoscun uledituw giju jiiko tuev efoneli jisi rulac. Ewkizpur obzuwkup ho sal kikja moz dosocoh furi kahfejuca rar uteoh wuwdow aw wutu tapof sefnittu koekse. Felenjo mazetasu kori rih ajuke cecac agaezor gihmu wizapiw felhasgi mi iji sufeg bep towwodaz fat."
  },
  "apiKey": "fe064ba0b536805c96b8d4909a97f678885ad2a63871bde3ee94b84dea72afea",
  "currency": {
    "code": "MRO",
    "name": "Mauritania Ouguiya"
  }
}