{
  "name": "Dorothy Beck",
  "age": 49,
  "address": {
    "street": "Peivi Trail",
    "city": "Emewatam",
    "state": "AR",
    "zip": "35851"
  },
  "contact": {
    "phone": "(853) 230-8869",
    "servicePhone": "800895179"
  },
  "birthday": "1981-01-19T03:34:18.248Z",
  "ip": "49.172.133.72",
  "foo": "bar",
  "profile": {
    "about": "Hihe sop gos walo geonwaz juuw zazefub jizog fabimcum cis ukemo if ri eni of. Juejodeb jivlas caga letre foacubi vov jis salmo uvutef sivlajmi ufu agnuwsam okfuc huirnu iserihkic. It pochu wikoduli eve jeegiva zonu ded jaipasi zic pibkec dul kapbuge tak.",
    "bio": "Cokdupe idmig dimlal gumucunuz oreboihi afroofe ev lizvaj odgec wa il vikseni imaew. Kaha hotmipmon fibi vam ruzvif weno viswocu desi kedekka eb jelhiw ke mopfuhoji pefarfod mevjizir. Fe fiwniw ki edmo igurpi tujfi jambi ve bi co ocaboswid zowij otu. Ur hefloj ciser ufu awrowsa kem atoarced ul ibisu getez random ojocer dikce."
  },
  "apiKey": "9a2d4c6fc5defdbd723b2788460c494acb08a3d49e0d1729da25181a017c2bb1",
  "currency": {
    "code": "KGS",
    "name": "Kyrgyzstan Som"
  }
}